datrie.cpython-38-darwin.so
ant_datrie-0.8.5.dist-info/COPYING
ant_datrie-0.8.5.dist-info/METADATA
ant_datrie-0.8.5.dist-info/WHEEL
ant_datrie-0.8.5.dist-info/top_level.txt
ant_datrie-0.8.5.dist-info/RECORD
